README.md
setup.py
ustorage/__init__.py
ustorage/bases.py
ustorage/exceptions.py
ustorage/s3.py
ustorage.egg-info/PKG-INFO
ustorage.egg-info/SOURCES.txt
ustorage.egg-info/dependency_links.txt
ustorage.egg-info/requires.txt
ustorage.egg-info/top_level.txt
ustorage.egg-info/zip-safe
ustorage/utils/__init__.py
ustorage/utils/files.py