Metadata-Version: 2.1
Name: ustorage
Version: 0.1.0
Summary: Unified Storage Interface for Python.
Home-page: https://github.com/wonderbeyond/ustorage
Author: wonderbeyond
Author-email: wonderbeyond@gmail.com
License: UNKNOWN
Platform: UNKNOWN
Classifier: Programming Language :: Python :: 2
Classifier: Programming Language :: Python :: 3
Classifier: License :: OSI Approved :: Apache Software License
Classifier: Operating System :: OS Independent
Provides-Extra: s3
